[
	{
		"pid" : 0,
		"title" : "Blues Singer",
		"image" : "blues_singer.jpg",
		"subalbum" : [
			{
				"pid" : 0,
				"title" : "Another Realm",
				"image" : "another_realm.jpg"
			},
			{
				"pid" : 1,
				"title" : "Ascendant",
				"image" : "ascendant.jpg"
			},
			{
				"pid" : 2,
				"title" : "Ascent",
				"image" : "ascent.jpg"
			}
		]
	},
	{
		"pid" : 1,
		"title" : "Destiny",
		"image" : "destiny.jpg",
		"subalbum" : [
			{
				"pid" : 0,
				"title" : "Cathedral of Trees",
				"image" : "cathedral_of_trees.jpg"
			},
			{
				"pid" : 1,
				"title" : "Come Up Here",
				"image" : "come_up_here.jpg"
			},
			{
				"pid" : 2,
				"title" : "Crystal Forest",
				"image" : "crystal_forest.jpg"
			}
		]
	},
	{
		"pid" : 2,
		"title" : "Eagle",
		"image" : "eagle.jpg",
		"subalbum" : [
			{
				"pid" : 0,
				"title" : "Curved Road",
				"image" : "curved_road.jpg"
			},
			{
				"pid" : 1,
				"title" : "Dawn Breaking",
				"image" : "dawn_breaking.jpg"
			},
			{
				"pid" : 2,
				"title" : "Dawn",
				"image" : "dawn.jpg"
			}
		]
	},
	{
		"pid" : 3,
		"title" : "Evening Harvest",
		"image" : "evening_harvest.jpg",
		"subalbum" : [
			{
				"pid" : 0,
				"title" : "Destiny",
				"image" : "destiny.jpg"
			},
			{
				"pid" : 1,
				"title" : "Destiny2",
				"image" : "destiny2.jpg"
			},
			{
				"pid" : 2,
				"title" : "Eagle Rising",
				"image" : "eagle_rising.jpg"
			}
		]
	},
	{
		"pid" : 4,
		"title" : "Home",
		"image" : "home2.jpg",
		"subalbum" : [
			{
				"pid" : 0,
				"title" : "Enclave",
				"image" : "enclave.jpg"
			},
			{
				"pid" : 1,
				"title" : "Enter In",
				"image" : "enter_in.jpg"
			},
			{
				"pid" : 2,
				"title" : "Evening Harvest",
				"image" : "evening_harvest.jpg"
			}
		]
	},
	{
		"pid" : 5,
		"title" : "River Flow",
		"image" : "river_flow.jpg",
		"subalbum" : [
			{
				"pid" : 0,
				"title" : "Expanse",
				"image" : "expanse.jpg"
			},
			{
				"pid" : 1,
				"title" : "Fathers Blessing",
				"image" : "fathers_blessing.jpg"
			},
			{
				"pid" : 2,
				"title" : "Fathers House",
				"image" : "fathers_house.jpg"
			}
		]
	},
	{
		"pid" : 6,
		"title" : "Secret Place",
		"image" : "secret_place.jpg",
		"subalbum" : [
			{
				"pid" : 0,
				"title" : "First Light",
				"image" : "first_light.jpg"
			},
			{
				"pid" : 1,
				"title" : "Forest Path",
				"image" : "forest_path.jpg"
			},
			{
				"pid" : 2,
				"title" : "Gateway",
				"image" : "gateway.jpg"
			}
		]
	},
	{
		"pid" : 7,
		"title" : "Tin Mine",
		"image" : "tin_mine.jpg",
		"subalbum" : [
			{
				"pid" : 0,
				"title" : "Homeward Flight",
				"image" : "homeward_flight.jpg"
			},
			{
				"pid" : 1,
				"title" : "Nightfall",
				"image" : "nightfall.jpg"
			},
			{
				"pid" : 2,
				"title" : "Oil",
				"image" : "oil.jpg"
			}
		]
	}
]